[
    {
        "name": "Fort Raptor",
        "fort": "fort-raptor",
        "description": "Beast upon this world!",
        "layout": "Standard Layout",
        "slug": "fort-raptor-standard-layout",
        "imageUrl": "https://i.imgur.com/AuDy2KV.jpeg",
        "premium": false,
        "obtain_percentage": 7,
        "power": 20,
        "ammunition": 27,
        "soldiers": 4,
        "hitpoints": 900,
        "defense_slots": 1,
        "weapon_slots": 4,
        "utility_slots": 2,
        "multi_slots": 0
    },
    {
        "name": "Fort Raptor",
        "fort": "fort-raptor",
        "description": "Beast upon this world!",
        "layout": "Extra Weapon & Concrete Layout",
        "slug": "fort-raptor-extra-weapon-concrete-layout",
        "imageUrl": "https://i.imgur.com/j7bizr5.jpeg",
        "premium": true,
        "obtain_percentage": 7,
        "power": 22,
        "ammunition": 32,
        "soldiers": 4,
        "hitpoints": 100,
        "defense_slots": 1,
        "weapon_slots": 5,
        "utility_slots": 2,
        "multi_slots": 0
    },
    {
        "name": "Fort Raptor",
        "fort": "fort-raptor",
        "description": "Beast upon this world!",
        "layout": "Extra Defense & Power Layout",
        "slug": "fort-raptor-extra-defense-power-layout",
        "imageUrl": "https://i.imgur.com/mMmoBpZ.jpeg",
        "premium": true,
        "obtain_percentage": 7,
        "power": 25,
        "ammunition": 27,
        "soldiers": 4,
        "hitpoints": 900,
        "defense_slots": 2,
        "weapon_slots": 4,
        "utility_slots": 3,
        "multi_slots": 0
    },
    {
        "name": "Fort Raptor",
        "fort": "fort-raptor",
        "description": "Beast upon this world!",
        "layout": "Extra Manpower & Cover Layout",
        "slug": "fort-raptor-extra-manpower-cover-layout",
        "imageUrl": "https://i.imgur.com/SVVi9ZL.jpeg",
        "premium": true,
        "obtain_percentage": 7,
        "power": 22,
        "ammunition": 28,
        "soldiers": 5,
        "hitpoints": 800,
        "defense_slots": 1,
        "weapon_slots": 3,
        "utility_slots": 3,
        "multi_slots": 1
    },
    {
        "name": "Fort Sycamore",
        "fort": "fort-sycamore",
        "description": "Cut them all down!",
        "layout": "Standard Layout",
        "slug": "fort-sycamore-standard-layout",
        "imageUrl": "https://i.imgur.com/sixvBR5.jpeg",
        "premium": false,
        "obtain_percentage": 16,
        "power": 25,
        "ammunition": 31,
        "soldiers": 5,
        "hitpoints": 1100,
        "defense_slots": 1,
        "weapon_slots": 5,
        "utility_slots": 3,
        "multi_slots": 0
    },
    {
        "name": "Fort Sycamore",
        "fort": "fort-sycamore",
        "description": "Cut them all down!",
        "layout": "Extra Weapon & Concrete Layout",
        "slug": "fort-sycamore-extra-weapon-concrete-layout",
        "imageUrl": "https://i.imgur.com/LMfmOfu.jpeg",
        "premium": true,
        "obtain_percentage": 16,
        "power": 27,
        "ammunition": 37,
        "soldiers": 5,
        "hitpoints": 1300,
        "defense_slots": 1,
        "weapon_slots": 6,
        "utility_slots": 3,
        "multi_slots": 0
    },
    {
        "name": "Fort Sycamore",
        "fort": "fort-sycamore",
        "description": "Cut them all down!",
        "layout": "Extra Defense & Power Layout",
        "slug": "fort-sycamore-extra-defense-power-layout",
        "imageUrl": "https://i.imgur.com/yHH8iqJ.jpeg",
        "premium": true,
        "obtain_percentage": 16,
        "power": 29,
        "ammunition": 31,
        "soldiers": 5,
        "hitpoints": 1100,
        "defense_slots": 2,
        "weapon_slots": 5,
        "utility_slots": 4,
        "multi_slots": 0
    },
    {
        "name": "Fort Sycamore",
        "fort": "fort-sycamore",
        "description": "Cut them all down!",
        "layout": "Extra Manpower & Cover Layout",
        "slug": "fort-sycamore-extra-manpower-cover-layout",
        "imageUrl": "https://i.imgur.com/DBqhs3z.jpeg",
        "premium": true,
        "obtain_percentage": 16,
        "power": 27,
        "ammunition": 32,
        "soldiers": 6,
        "hitpoints": 1000,
        "defense_slots": 1,
        "weapon_slots": 3,
        "utility_slots": 4,
        "multi_slots": 2
    },
    {
        "name": "The Spire",
        "fort": "the-spire",
        "description": "Stand your ground!",
        "layout": "Extra Weapon & Concrete Layout",
        "slug": "the-spire-extra-weapon-concrete-layout",
        "imageUrl": "https://i.imgur.com/m7HGy2w.jpeg",
        "premium": true,
        "obtain_percentage": 27,
        "power": 30,
        "ammunition": 42,
        "soldiers": 5,
        "hitpoints": 1500,
        "defense_slots": 2,
        "weapon_slots": 6,
        "utility_slots": 4,
        "multi_slots": 1
    },
    {
        "name": "The Spire",
        "fort": "the-spire",
        "description": "Stand your ground!",
        "layout": "Extra Defense & Power Layout",
        "slug": "the-spire-extra-defense-power-layout",
        "imageUrl": "https://i.imgur.com/8rVCXH6.jpeg",
        "premium": true,
        "obtain_percentage": 27,
        "power": 34,
        "ammunition": 34,
        "soldiers": 5,
        "hitpoints": 1300,
        "defense_slots": 3,
        "weapon_slots": 5,
        "utility_slots": 5,
        "multi_slots": 1
    },
    {
        "name": "The Spire",
        "fort": "the-spire",
        "description": "Stand your ground!",
        "layout": "Extra Manpower & Cover Layout",
        "slug": "the-spire-extra-manpower-cover-layout",
        "imageUrl": "https://i.imgur.com/erETvsJ.jpeg",
        "premium": true,
        "obtain_percentage": 27,
        "power": 30,
        "ammunition": 34,
        "soldiers": 6,
        "hitpoints": 1200,
        "defense_slots": 2,
        "weapon_slots": 4,
        "utility_slots": 5,
        "multi_slots": 2
    },
    {
        "name": "Fortress Scarabeus",
        "fort": "fortress-scarabeus",
        "description": "Eternal peace in perpetual war.",
        "layout": "Extra Weapon & Concrete Layout",
        "slug": "fortress-scarabeus-extra-weapon-concrete-layout",
        "imageUrl": "https://i.imgur.com/dotMQDr.jpeg",
        "premium": true,
        "obtain_percentage": 38,
        "power": 33,
        "ammunition": 45,
        "soldiers": 5,
        "hitpoints": 1600,
        "defense_slots": 2,
        "weapon_slots": 7,
        "utility_slots": 5,
        "multi_slots": 0
    },
    {
        "name": "Fortress Scarabeus",
        "fort": "fortress-scarabeus",
        "description": "Eternal peace in perpetual war.",
        "layout": "Extra Defense & Power Layout",
        "slug": "fortress-scarabeus-extra-defense-power-layout",
        "imageUrl": "https://i.imgur.com/pOGsNgw.jpeg",
        "premium": true,
        "obtain_percentage": 38,
        "power": 37,
        "ammunition": 37,
        "soldiers": 5,
        "hitpoints": 1400,
        "defense_slots": 3,
        "weapon_slots": 6,
        "utility_slots": 6,
        "multi_slots": 0
    },
    {
        "name": "Fortress Scarabeus",
        "fort": "fortress-scarabeus",
        "description": "Eternal peace in perpetual war.",
        "layout": "Extra Manpower & Cover Layout",
        "slug": "fortress-scarabeus-extra-manpower-cover-layout",
        "imageUrl": "https://i.imgur.com/QUfqT4C.jpeg",
        "premium": true,
        "obtain_percentage": 38,
        "power": 33,
        "ammunition": 37,
        "soldiers": 6,
        "hitpoints": 1300,
        "defense_slots": 2,
        "weapon_slots": 5,
        "utility_slots": 6,
        "multi_slots": 1
    },
    {
        "name": "Fortress Falcon",
        "fort": "fortress-falcon",
        "description": "Swoop in for the kill!",
        "layout": "Extra Weapon & Concrete Layout",
        "slug": "fortress-falcon-extra-weapon-concrete-layout",
        "imageUrl": "https://i.imgur.com/yOgfrAk.jpeg",
        "premium": true,
        "obtain_percentage": 54,
        "power": 36,
        "ammunition": 50,
        "soldiers": 6,
        "hitpoints": 1700,
        "defense_slots": 2,
        "weapon_slots": 8,
        "utility_slots": 5,
        "multi_slots": 0
    },
    {
        "name": "Fortress Falcon",
        "fort": "fortress-falcon",
        "description": "Swoop in for the kill!",
        "layout": "Extra Defense & Power Layout",
        "slug": "fortress-falcon-extra-defense-power-layout",
        "imageUrl": "https://i.imgur.com/z7sdzBf.jpeg",
        "premium": true,
        "obtain_percentage": 54,
        "power": 40,
        "ammunition": 40,
        "soldiers": 6,
        "hitpoints": 1500,
        "defense_slots": 3,
        "weapon_slots": 6,
        "utility_slots": 6,
        "multi_slots": 1
    },
    {
        "name": "Fortress Falcon",
        "fort": "fortress-falcon",
        "description": "Swoop in for the kill!",
        "layout": "Extra Manpower Layout",
        "slug": "fortress-falcon-extra-manpower-layout",
        "imageUrl": "https://i.imgur.com/3sDyoSw.jpeg",
        "premium": true,
        "obtain_percentage": 54,
        "power": 36,
        "ammunition": 40,
        "soldiers": 7,
        "hitpoints": 1400,
        "defense_slots": 2,
        "weapon_slots": 6,
        "utility_slots": 6,
        "multi_slots": 1
    },
    {
        "name": "Fortress Resolution",
        "fort": "fortress-resolution",
        "description": "Stronger will shall triumph!",
        "layout": "Extra Ammunition & Concrete Layout",
        "slug": "fortress-resolution-extra-ammunition-concrete-layout",
        "imageUrl": "https://i.imgur.com/AMbiO5p.jpeg",
        "premium": true,
        "obtain_percentage": 73,
        "power": 40,
        "ammunition": 54,
        "soldiers": 7,
        "hitpoints": 1800,
        "defense_slots": 3,
        "weapon_slots": 8,
        "utility_slots": 7,
        "multi_slots": 0
    },
    {
        "name": "Fortress Resolution",
        "fort": "fortress-resolution",
        "description": "Stronger will shall triumph!",
        "layout": "Extra Power Layout",
        "slug": "fortress-resolution-extra-power-layout",
        "imageUrl": "https://i.imgur.com/fcb0EBP.jpeg",
        "premium": true,
        "obtain_percentage": 73,
        "power": 46,
        "ammunition": 42,
        "soldiers": 7,
        "hitpoints": 1600,
        "defense_slots": 3,
        "weapon_slots": 8,
        "utility_slots": 7,
        "multi_slots": 0
    },
    {
        "name": "Fortress Resolution",
        "fort": "fortress-resolution",
        "description": "Stronger will shall triumph!",
        "layout": "Extra Manpower & Cover Layout",
        "slug": "fortress-resolution-extra-manpower-cover-layout",
        "imageUrl": "https://i.imgur.com/p6OaZzt.jpeg",
        "premium": true,
        "obtain_percentage": 73,
        "power": 40,
        "ammunition": 42,
        "soldiers": 8,
        "hitpoints": 1600,
        "defense_slots": 3,
        "weapon_slots": 7,
        "utility_slots": 7,
        "multi_slots": 1
    },
    {
        "name": "Fortress Rubicon",
        "fort": "fortress-rubicon",
        "description": "The die is cast.",
        "layout": "Extra Weapon & Concrete Layout",
        "slug": "fortress-rubicon-extra-weapon-concrete-layout",
        "imageUrl": "https://i.imgur.com/KTUfPW4.jpeg",
        "premium": true,
        "obtain_percentage": 99,
        "power": 48,
        "ammunition": 62,
        "soldiers": 8,
        "hitpoints": 2000,
        "defense_slots": 3,
        "weapon_slots": 8,
        "utility_slots": 9,
        "multi_slots": 1
    },
    {
        "name": "Fortress Rubicon",
        "fort": "fortress-rubicon",
        "description": "The die is cast.",
        "layout": "Extra Defense & Power Layout",
        "slug": "fortress-rubicon-extra-defense-power-layout",
        "imageUrl": "https://i.imgur.com/2tUGwoC.jpeg",
        "premium": true,
        "obtain_percentage": 99,
        "power": 54,
        "ammunition": 48,
        "soldiers": 8,
        "hitpoints": 1800,
        "defense_slots": 4,
        "weapon_slots": 7,
        "utility_slots": 10,
        "multi_slots": 1
    },
    {
        "name": "Fortress Rubicon",
        "fort": "fortress-rubicon",
        "description": "The die is cast.",
        "layout": "Extra Manpower & Cover Layout",
        "slug": "fortress-rubicon-extra-manpower-cover-layout",
        "imageUrl": "https://i.imgur.com/mZ46Coi.jpeg",
        "premium": true,
        "obtain_percentage": 99,
        "power": 48,
        "ammunition": 48,
        "soldiers": 9,
        "hitpoints": 1800,
        "defense_slots": 3,
        "weapon_slots": 7,
        "utility_slots": 10,
        "multi_slots": 1
    }
]